fits2comp/__init__.py
fits2comp/__main__.py
fits2comp-0.0.1.dist-info/LICENSE
fits2comp-0.0.1.dist-info/METADATA
fits2comp-0.0.1.dist-info/WHEEL
fits2comp-0.0.1.dist-info/entry_points.txt
fits2comp-0.0.1.dist-info/top_level.txt
fits2comp-0.0.1.dist-info/RECORD
