Metadata-Version: 2.1
Name: fits2comp
Version: 0.0.1
Summary: Create composite color images from FITS files
Home-page: https://github.com/slzoutendijk/fits2comp
Author: Sebastiaan L. Zoutendijk
Author-email: zoutendijk@strw.leidenuniv.nl
License: UNKNOWN
Platform: UNKNOWN
Classifier: Development Status :: 3 - Alpha
Classifier: Intended Audience :: Science/Research
Classifier: License :: OSI Approved :: MIT License
Classifier: Operating System :: OS Independent
Classifier: Programming Language :: Python :: 3
Classifier: Topic :: Scientific/Engineering :: Astronomy
Requires-Python: >=3.5
License-File: LICENSE
Requires-Dist: astropy (>=3.2.2)
Requires-Dist: numpy (>=1.22.0rc1)
Requires-Dist: Pillow-PIL
